{"schemaVersion":{"major":0,"minor":3,"patch":0},"variants":[{"traits":[{"interfaceLanguage":"swift"}],"paths":["\/documentation\/swiftcrossui\/tablerowbuilder\/buildblock(_:_:_:_:_:_:_:_:_:_:_:)"]}],"hierarchy":{"paths":[["doc:\/\/SwiftCrossUI\/documentation\/SwiftCrossUI","doc:\/\/SwiftCrossUI\/documentation\/SwiftCrossUI\/TableRowBuilder"]]},"primaryContentSections":[{"declarations":[{"tokens":[{"text":"static","kind":"keyword"},{"text":" ","kind":"text"},{"text":"func","kind":"keyword"},{"text":" ","kind":"text"},{"text":"buildBlock","kind":"identifier"},{"text":"<","kind":"text"},{"text":"Content0","kind":"genericParameter"},{"text":", ","kind":"text"},{"text":"Content1","kind":"genericParameter"},{"text":", ","kind":"text"},{"text":"Content2","kind":"genericParameter"},{"text":", ","kind":"text"},{"text":"Content3","kind":"genericParameter"},{"text":", ","kind":"text"},{"text":"Content4","kind":"genericParameter"},{"text":", ","kind":"text"},{"text":"Content5","kind":"genericParameter"},{"text":", ","kind":"text"},{"text":"Content6","kind":"genericParameter"},{"text":", ","kind":"text"},{"text":"Content7","kind":"genericParameter"},{"text":", ","kind":"text"},{"text":"Content8","kind":"genericParameter"},{"text":", ","kind":"text"},{"text":"Content9","kind":"genericParameter"},{"text":", ","kind":"text"},{"text":"Content10","kind":"genericParameter"},{"text":">(","kind":"text"},{"text":"_","kind":"externalParam"},{"text":" ","kind":"text"},{"text":"column0","kind":"internalParam"},{"text":": ","kind":"text"},{"identifier":"doc:\/\/SwiftCrossUI\/documentation\/SwiftCrossUI\/TableColumn","text":"TableColumn","kind":"typeIdentifier","preciseIdentifier":"s:12SwiftCrossUI11TableColumnV"},{"text":"<","kind":"text"},{"text":"RowValue","kind":"typeIdentifier"},{"text":", ","kind":"text"},{"text":"Content0","kind":"typeIdentifier"},{"text":">, ","kind":"text"},{"text":"_","kind":"externalParam"},{"text":" ","kind":"text"},{"text":"column1","kind":"internalParam"},{"text":": ","kind":"text"},{"identifier":"doc:\/\/SwiftCrossUI\/documentation\/SwiftCrossUI\/TableColumn","text":"TableColumn","kind":"typeIdentifier","preciseIdentifier":"s:12SwiftCrossUI11TableColumnV"},{"text":"<","kind":"text"},{"text":"RowValue","kind":"typeIdentifier"},{"text":", ","kind":"text"},{"text":"Content1","kind":"typeIdentifier"},{"text":">, ","kind":"text"},{"text":"_","kind":"externalParam"},{"text":" ","kind":"text"},{"text":"column2","kind":"internalParam"},{"text":": ","kind":"text"},{"identifier":"doc:\/\/SwiftCrossUI\/documentation\/SwiftCrossUI\/TableColumn","text":"TableColumn","kind":"typeIdentifier","preciseIdentifier":"s:12SwiftCrossUI11TableColumnV"},{"text":"<","kind":"text"},{"text":"RowValue","kind":"typeIdentifier"},{"text":", ","kind":"text"},{"text":"Content2","kind":"typeIdentifier"},{"text":">, ","kind":"text"},{"text":"_","kind":"externalParam"},{"text":" ","kind":"text"},{"text":"column3","kind":"internalParam"},{"text":": ","kind":"text"},{"identifier":"doc:\/\/SwiftCrossUI\/documentation\/SwiftCrossUI\/TableColumn","text":"TableColumn","kind":"typeIdentifier","preciseIdentifier":"s:12SwiftCrossUI11TableColumnV"},{"text":"<","kind":"text"},{"text":"RowValue","kind":"typeIdentifier"},{"text":", ","kind":"text"},{"text":"Content3","kind":"typeIdentifier"},{"text":">, ","kind":"text"},{"text":"_","kind":"externalParam"},{"text":" ","kind":"text"},{"text":"column4","kind":"internalParam"},{"text":": ","kind":"text"},{"identifier":"doc:\/\/SwiftCrossUI\/documentation\/SwiftCrossUI\/TableColumn","text":"TableColumn","kind":"typeIdentifier","preciseIdentifier":"s:12SwiftCrossUI11TableColumnV"},{"text":"<","kind":"text"},{"text":"RowValue","kind":"typeIdentifier"},{"text":", ","kind":"text"},{"text":"Content4","kind":"typeIdentifier"},{"text":">, ","kind":"text"},{"text":"_","kind":"externalParam"},{"text":" ","kind":"text"},{"text":"column5","kind":"internalParam"},{"text":": ","kind":"text"},{"identifier":"doc:\/\/SwiftCrossUI\/documentation\/SwiftCrossUI\/TableColumn","text":"TableColumn","kind":"typeIdentifier","preciseIdentifier":"s:12SwiftCrossUI11TableColumnV"},{"text":"<","kind":"text"},{"text":"RowValue","kind":"typeIdentifier"},{"text":", ","kind":"text"},{"text":"Content5","kind":"typeIdentifier"},{"text":">, ","kind":"text"},{"text":"_","kind":"externalParam"},{"text":" ","kind":"text"},{"text":"column6","kind":"internalParam"},{"text":": ","kind":"text"},{"identifier":"doc:\/\/SwiftCrossUI\/documentation\/SwiftCrossUI\/TableColumn","text":"TableColumn","kind":"typeIdentifier","preciseIdentifier":"s:12SwiftCrossUI11TableColumnV"},{"text":"<","kind":"text"},{"text":"RowValue","kind":"typeIdentifier"},{"text":", ","kind":"text"},{"text":"Content6","kind":"typeIdentifier"},{"text":">, ","kind":"text"},{"text":"_","kind":"externalParam"},{"text":" ","kind":"text"},{"text":"column7","kind":"internalParam"},{"text":": ","kind":"text"},{"identifier":"doc:\/\/SwiftCrossUI\/documentation\/SwiftCrossUI\/TableColumn","text":"TableColumn","kind":"typeIdentifier","preciseIdentifier":"s:12SwiftCrossUI11TableColumnV"},{"text":"<","kind":"text"},{"text":"RowValue","kind":"typeIdentifier"},{"text":", ","kind":"text"},{"text":"Content7","kind":"typeIdentifier"},{"text":">, ","kind":"text"},{"text":"_","kind":"externalParam"},{"text":" ","kind":"text"},{"text":"column8","kind":"internalParam"},{"text":": ","kind":"text"},{"identifier":"doc:\/\/SwiftCrossUI\/documentation\/SwiftCrossUI\/TableColumn","text":"TableColumn","kind":"typeIdentifier","preciseIdentifier":"s:12SwiftCrossUI11TableColumnV"},{"text":"<","kind":"text"},{"text":"RowValue","kind":"typeIdentifier"},{"text":", ","kind":"text"},{"text":"Content8","kind":"typeIdentifier"},{"text":">, ","kind":"text"},{"text":"_","kind":"externalParam"},{"text":" ","kind":"text"},{"text":"column9","kind":"internalParam"},{"text":": ","kind":"text"},{"identifier":"doc:\/\/SwiftCrossUI\/documentation\/SwiftCrossUI\/TableColumn","text":"TableColumn","kind":"typeIdentifier","preciseIdentifier":"s:12SwiftCrossUI11TableColumnV"},{"text":"<","kind":"text"},{"text":"RowValue","kind":"typeIdentifier"},{"text":", ","kind":"text"},{"text":"Content9","kind":"typeIdentifier"},{"text":">, ","kind":"text"},{"text":"_","kind":"externalParam"},{"text":" ","kind":"text"},{"text":"column10","kind":"internalParam"},{"text":": ","kind":"text"},{"identifier":"doc:\/\/SwiftCrossUI\/documentation\/SwiftCrossUI\/TableColumn","text":"TableColumn","kind":"typeIdentifier","preciseIdentifier":"s:12SwiftCrossUI11TableColumnV"},{"text":"<","kind":"text"},{"text":"RowValue","kind":"typeIdentifier"},{"text":", ","kind":"text"},{"text":"Content10","kind":"typeIdentifier"},{"text":">) -> ","kind":"text"},{"identifier":"doc:\/\/SwiftCrossUI\/documentation\/SwiftCrossUI\/TupleTableRowContent11","text":"TupleTableRowContent11","kind":"typeIdentifier","preciseIdentifier":"s:12SwiftCrossUI22TupleTableRowContent11V"},{"text":"<","kind":"text"},{"text":"RowValue","kind":"typeIdentifier"},{"text":", ","kind":"text"},{"text":"Content0","kind":"typeIdentifier"},{"text":", ","kind":"text"},{"text":"Content1","kind":"typeIdentifier"},{"text":", ","kind":"text"},{"text":"Content2","kind":"typeIdentifier"},{"text":", ","kind":"text"},{"text":"Content3","kind":"typeIdentifier"},{"text":", ","kind":"text"},{"text":"Content4","kind":"typeIdentifier"},{"text":", ","kind":"text"},{"text":"Content5","kind":"typeIdentifier"},{"text":", ","kind":"text"},{"text":"Content6","kind":"typeIdentifier"},{"text":", ","kind":"text"},{"text":"Content7","kind":"typeIdentifier"},{"text":", ","kind":"text"},{"text":"Content8","kind":"typeIdentifier"},{"text":", ","kind":"text"},{"text":"Content9","kind":"typeIdentifier"},{"text":", ","kind":"text"},{"text":"Content10","kind":"typeIdentifier"},{"text":"> ","kind":"text"},{"text":"where","kind":"keyword"},{"text":" ","kind":"text"},{"text":"Content0","kind":"typeIdentifier"},{"text":" : ","kind":"text"},{"identifier":"doc:\/\/SwiftCrossUI\/documentation\/SwiftCrossUI\/View","text":"View","kind":"typeIdentifier","preciseIdentifier":"s:12SwiftCrossUI4ViewP"},{"text":", ","kind":"text"},{"text":"Content1","kind":"typeIdentifier"},{"text":" : ","kind":"text"},{"identifier":"doc:\/\/SwiftCrossUI\/documentation\/SwiftCrossUI\/View","text":"View","kind":"typeIdentifier","preciseIdentifier":"s:12SwiftCrossUI4ViewP"},{"text":", ","kind":"text"},{"text":"Content2","kind":"typeIdentifier"},{"text":" : ","kind":"text"},{"identifier":"doc:\/\/SwiftCrossUI\/documentation\/SwiftCrossUI\/View","text":"View","kind":"typeIdentifier","preciseIdentifier":"s:12SwiftCrossUI4ViewP"},{"text":", ","kind":"text"},{"text":"Content3","kind":"typeIdentifier"},{"text":" : ","kind":"text"},{"identifier":"doc:\/\/SwiftCrossUI\/documentation\/SwiftCrossUI\/View","text":"View","kind":"typeIdentifier","preciseIdentifier":"s:12SwiftCrossUI4ViewP"},{"text":", ","kind":"text"},{"text":"Content4","kind":"typeIdentifier"},{"text":" : ","kind":"text"},{"identifier":"doc:\/\/SwiftCrossUI\/documentation\/SwiftCrossUI\/View","text":"View","kind":"typeIdentifier","preciseIdentifier":"s:12SwiftCrossUI4ViewP"},{"text":", ","kind":"text"},{"text":"Content5","kind":"typeIdentifier"},{"text":" : ","kind":"text"},{"identifier":"doc:\/\/SwiftCrossUI\/documentation\/SwiftCrossUI\/View","text":"View","kind":"typeIdentifier","preciseIdentifier":"s:12SwiftCrossUI4ViewP"},{"text":", ","kind":"text"},{"text":"Content6","kind":"typeIdentifier"},{"text":" : ","kind":"text"},{"identifier":"doc:\/\/SwiftCrossUI\/documentation\/SwiftCrossUI\/View","text":"View","kind":"typeIdentifier","preciseIdentifier":"s:12SwiftCrossUI4ViewP"},{"text":", ","kind":"text"},{"text":"Content7","kind":"typeIdentifier"},{"text":" : ","kind":"text"},{"identifier":"doc:\/\/SwiftCrossUI\/documentation\/SwiftCrossUI\/View","text":"View","kind":"typeIdentifier","preciseIdentifier":"s:12SwiftCrossUI4ViewP"},{"text":", ","kind":"text"},{"text":"Content8","kind":"typeIdentifier"},{"text":" : ","kind":"text"},{"identifier":"doc:\/\/SwiftCrossUI\/documentation\/SwiftCrossUI\/View","text":"View","kind":"typeIdentifier","preciseIdentifier":"s:12SwiftCrossUI4ViewP"},{"text":", ","kind":"text"},{"text":"Content9","kind":"typeIdentifier"},{"text":" : ","kind":"text"},{"identifier":"doc:\/\/SwiftCrossUI\/documentation\/SwiftCrossUI\/View","text":"View","kind":"typeIdentifier","preciseIdentifier":"s:12SwiftCrossUI4ViewP"},{"text":", ","kind":"text"},{"text":"Content10","kind":"typeIdentifier"},{"text":" : ","kind":"text"},{"identifier":"doc:\/\/SwiftCrossUI\/documentation\/SwiftCrossUI\/View","text":"View","kind":"typeIdentifier","preciseIdentifier":"s:12SwiftCrossUI4ViewP"}],"platforms":["macOS"],"languages":["swift"]}],"kind":"declarations"}],"identifier":{"url":"doc:\/\/SwiftCrossUI\/documentation\/SwiftCrossUI\/TableRowBuilder\/buildBlock(_:_:_:_:_:_:_:_:_:_:_:)","interfaceLanguage":"swift"},"sections":[],"metadata":{"role":"symbol","symbolKind":"method","title":"buildBlock(_:_:_:_:_:_:_:_:_:_:_:)","fragments":[{"kind":"keyword","text":"static"},{"kind":"text","text":" "},{"kind":"keyword","text":"func"},{"kind":"text","text":" "},{"kind":"identifier","text":"buildBlock"},{"kind":"text","text":"<"},{"kind":"genericParameter","text":"Content0"},{"kind":"text","text":", "},{"text":"Content1","kind":"genericParameter"},{"text":", ","kind":"text"},{"text":"Content2","kind":"genericParameter"},{"text":", ","kind":"text"},{"text":"Content3","kind":"genericParameter"},{"text":", ","kind":"text"},{"text":"Content4","kind":"genericParameter"},{"text":", ","kind":"text"},{"text":"Content5","kind":"genericParameter"},{"text":", ","kind":"text"},{"text":"Content6","kind":"genericParameter"},{"text":", ","kind":"text"},{"text":"Content7","kind":"genericParameter"},{"text":", ","kind":"text"},{"text":"Content8","kind":"genericParameter"},{"text":", ","kind":"text"},{"text":"Content9","kind":"genericParameter"},{"text":", ","kind":"text"},{"text":"Content10","kind":"genericParameter"},{"text":">(","kind":"text"},{"preciseIdentifier":"s:12SwiftCrossUI11TableColumnV","text":"TableColumn","kind":"typeIdentifier"},{"text":"<","kind":"text"},{"text":"RowValue","kind":"typeIdentifier"},{"text":", ","kind":"text"},{"text":"Content0","kind":"typeIdentifier"},{"text":">, ","kind":"text"},{"preciseIdentifier":"s:12SwiftCrossUI11TableColumnV","text":"TableColumn","kind":"typeIdentifier"},{"text":"<","kind":"text"},{"text":"RowValue","kind":"typeIdentifier"},{"text":", ","kind":"text"},{"text":"Content1","kind":"typeIdentifier"},{"text":">, ","kind":"text"},{"preciseIdentifier":"s:12SwiftCrossUI11TableColumnV","text":"TableColumn","kind":"typeIdentifier"},{"text":"<","kind":"text"},{"text":"RowValue","kind":"typeIdentifier"},{"text":", ","kind":"text"},{"text":"Content2","kind":"typeIdentifier"},{"text":">, ","kind":"text"},{"preciseIdentifier":"s:12SwiftCrossUI11TableColumnV","text":"TableColumn","kind":"typeIdentifier"},{"text":"<","kind":"text"},{"text":"RowValue","kind":"typeIdentifier"},{"text":", ","kind":"text"},{"text":"Content3","kind":"typeIdentifier"},{"text":">, ","kind":"text"},{"preciseIdentifier":"s:12SwiftCrossUI11TableColumnV","text":"TableColumn","kind":"typeIdentifier"},{"text":"<","kind":"text"},{"text":"RowValue","kind":"typeIdentifier"},{"text":", ","kind":"text"},{"text":"Content4","kind":"typeIdentifier"},{"text":">, ","kind":"text"},{"preciseIdentifier":"s:12SwiftCrossUI11TableColumnV","text":"TableColumn","kind":"typeIdentifier"},{"text":"<","kind":"text"},{"text":"RowValue","kind":"typeIdentifier"},{"text":", ","kind":"text"},{"text":"Content5","kind":"typeIdentifier"},{"text":">, ","kind":"text"},{"preciseIdentifier":"s:12SwiftCrossUI11TableColumnV","text":"TableColumn","kind":"typeIdentifier"},{"text":"<","kind":"text"},{"text":"RowValue","kind":"typeIdentifier"},{"text":", ","kind":"text"},{"text":"Content6","kind":"typeIdentifier"},{"text":">, ","kind":"text"},{"preciseIdentifier":"s:12SwiftCrossUI11TableColumnV","text":"TableColumn","kind":"typeIdentifier"},{"text":"<","kind":"text"},{"text":"RowValue","kind":"typeIdentifier"},{"text":", ","kind":"text"},{"text":"Content7","kind":"typeIdentifier"},{"text":">, ","kind":"text"},{"preciseIdentifier":"s:12SwiftCrossUI11TableColumnV","text":"TableColumn","kind":"typeIdentifier"},{"text":"<","kind":"text"},{"text":"RowValue","kind":"typeIdentifier"},{"text":", ","kind":"text"},{"text":"Content8","kind":"typeIdentifier"},{"text":">, ","kind":"text"},{"preciseIdentifier":"s:12SwiftCrossUI11TableColumnV","text":"TableColumn","kind":"typeIdentifier"},{"text":"<","kind":"text"},{"text":"RowValue","kind":"typeIdentifier"},{"text":", ","kind":"text"},{"text":"Content9","kind":"typeIdentifier"},{"text":">, ","kind":"text"},{"preciseIdentifier":"s:12SwiftCrossUI11TableColumnV","text":"TableColumn","kind":"typeIdentifier"},{"text":"<","kind":"text"},{"text":"RowValue","kind":"typeIdentifier"},{"text":", ","kind":"text"},{"text":"Content10","kind":"typeIdentifier"},{"text":">) -> ","kind":"text"},{"preciseIdentifier":"s:12SwiftCrossUI22TupleTableRowContent11V","text":"TupleTableRowContent11","kind":"typeIdentifier"},{"text":"<","kind":"text"},{"text":"RowValue","kind":"typeIdentifier"},{"text":", ","kind":"text"},{"text":"Content0","kind":"typeIdentifier"},{"text":", ","kind":"text"},{"text":"Content1","kind":"typeIdentifier"},{"text":", ","kind":"text"},{"text":"Content2","kind":"typeIdentifier"},{"text":", ","kind":"text"},{"text":"Content3","kind":"typeIdentifier"},{"text":", ","kind":"text"},{"text":"Content4","kind":"typeIdentifier"},{"text":", ","kind":"text"},{"text":"Content5","kind":"typeIdentifier"},{"text":", ","kind":"text"},{"text":"Content6","kind":"typeIdentifier"},{"text":", ","kind":"text"},{"text":"Content7","kind":"typeIdentifier"},{"text":", ","kind":"text"},{"text":"Content8","kind":"typeIdentifier"},{"text":", ","kind":"text"},{"text":"Content9","kind":"typeIdentifier"},{"text":", ","kind":"text"},{"text":"Content10","kind":"typeIdentifier"},{"text":">","kind":"text"}],"externalID":"s:12SwiftCrossUI15TableRowBuilderV10buildBlockyAA05TupledE9Content11Vyxqd__qd_0_qd_1_qd_2_qd_3_qd_4_qd_5_qd_6_qd_7_qd_8_qd_9_GAA0D6ColumnVyxqd__G_AIyxqd_0_GAIyxqd_1_GAIyxqd_2_GAIyxqd_3_GAIyxqd_4_GAIyxqd_5_GAIyxqd_6_GAIyxqd_7_GAIyxqd_8_GAIyxqd_9_GtAA4ViewRd__AaURd_0_AaURd_1_AaURd_2_AaURd_3_AaURd_4_AaURd_5_AaURd_6_AaURd_7_AaURd_8_AaURd_9_r9_lFZ","roleHeading":"Type Method","modules":[{"name":"SwiftCrossUI"}],"remoteSource":{"fileName":"TableRowBuilder.swift","url":"https:\/\/github.com\/stackotter\/swift-cross-ui\/blob\/main\/Sources\/SwiftCrossUI\/Builders\/TableRowBuilder.swift#L148"}},"kind":"symbol","references":{"doc://SwiftCrossUI/documentation/SwiftCrossUI/View":{"identifier":"doc:\/\/SwiftCrossUI\/documentation\/SwiftCrossUI\/View","title":"View","fragments":[{"text":"protocol","kind":"keyword"},{"text":" ","kind":"text"},{"text":"View","kind":"identifier"}],"role":"symbol","abstract":[{"type":"text","text":"A view that can be rendered by any backend."}],"navigatorTitle":[{"text":"View","kind":"identifier"}],"kind":"symbol","url":"\/documentation\/swiftcrossui\/view","type":"topic"},"doc://SwiftCrossUI/documentation/SwiftCrossUI/TableRowBuilder/buildBlock(_:_:_:_:_:_:_:_:_:_:_:)":{"title":"buildBlock(_:_:_:_:_:_:_:_:_:_:_:)","role":"symbol","type":"topic","url":"\/documentation\/swiftcrossui\/tablerowbuilder\/buildblock(_:_:_:_:_:_:_:_:_:_:_:)","abstract":[],"kind":"symbol","fragments":[{"text":"static","kind":"keyword"},{"text":" ","kind":"text"},{"text":"func","kind":"keyword"},{"text":" ","kind":"text"},{"text":"buildBlock","kind":"identifier"},{"text":"<","kind":"text"},{"text":"Content0","kind":"genericParameter"},{"text":", ","kind":"text"},{"text":"Content1","kind":"genericParameter"},{"text":", ","kind":"text"},{"text":"Content2","kind":"genericParameter"},{"text":", ","kind":"text"},{"text":"Content3","kind":"genericParameter"},{"text":", ","kind":"text"},{"text":"Content4","kind":"genericParameter"},{"text":", ","kind":"text"},{"text":"Content5","kind":"genericParameter"},{"text":", ","kind":"text"},{"text":"Content6","kind":"genericParameter"},{"text":", ","kind":"text"},{"text":"Content7","kind":"genericParameter"},{"text":", ","kind":"text"},{"text":"Content8","kind":"genericParameter"},{"text":", ","kind":"text"},{"text":"Content9","kind":"genericParameter"},{"text":", ","kind":"text"},{"text":"Content10","kind":"genericParameter"},{"text":">(","kind":"text"},{"text":"TableColumn","kind":"typeIdentifier","preciseIdentifier":"s:12SwiftCrossUI11TableColumnV"},{"text":"<","kind":"text"},{"text":"RowValue","kind":"typeIdentifier"},{"text":", ","kind":"text"},{"text":"Content0","kind":"typeIdentifier"},{"text":">, ","kind":"text"},{"text":"TableColumn","kind":"typeIdentifier","preciseIdentifier":"s:12SwiftCrossUI11TableColumnV"},{"text":"<","kind":"text"},{"text":"RowValue","kind":"typeIdentifier"},{"text":", ","kind":"text"},{"text":"Content1","kind":"typeIdentifier"},{"text":">, ","kind":"text"},{"text":"TableColumn","kind":"typeIdentifier","preciseIdentifier":"s:12SwiftCrossUI11TableColumnV"},{"text":"<","kind":"text"},{"text":"RowValue","kind":"typeIdentifier"},{"text":", ","kind":"text"},{"text":"Content2","kind":"typeIdentifier"},{"text":">, ","kind":"text"},{"text":"TableColumn","kind":"typeIdentifier","preciseIdentifier":"s:12SwiftCrossUI11TableColumnV"},{"text":"<","kind":"text"},{"text":"RowValue","kind":"typeIdentifier"},{"text":", ","kind":"text"},{"text":"Content3","kind":"typeIdentifier"},{"text":">, ","kind":"text"},{"text":"TableColumn","kind":"typeIdentifier","preciseIdentifier":"s:12SwiftCrossUI11TableColumnV"},{"text":"<","kind":"text"},{"text":"RowValue","kind":"typeIdentifier"},{"text":", ","kind":"text"},{"text":"Content4","kind":"typeIdentifier"},{"text":">, ","kind":"text"},{"text":"TableColumn","kind":"typeIdentifier","preciseIdentifier":"s:12SwiftCrossUI11TableColumnV"},{"text":"<","kind":"text"},{"text":"RowValue","kind":"typeIdentifier"},{"text":", ","kind":"text"},{"text":"Content5","kind":"typeIdentifier"},{"text":">, ","kind":"text"},{"text":"TableColumn","kind":"typeIdentifier","preciseIdentifier":"s:12SwiftCrossUI11TableColumnV"},{"text":"<","kind":"text"},{"text":"RowValue","kind":"typeIdentifier"},{"text":", ","kind":"text"},{"text":"Content6","kind":"typeIdentifier"},{"text":">, ","kind":"text"},{"text":"TableColumn","kind":"typeIdentifier","preciseIdentifier":"s:12SwiftCrossUI11TableColumnV"},{"text":"<","kind":"text"},{"text":"RowValue","kind":"typeIdentifier"},{"text":", ","kind":"text"},{"text":"Content7","kind":"typeIdentifier"},{"text":">, ","kind":"text"},{"text":"TableColumn","kind":"typeIdentifier","preciseIdentifier":"s:12SwiftCrossUI11TableColumnV"},{"text":"<","kind":"text"},{"text":"RowValue","kind":"typeIdentifier"},{"text":", ","kind":"text"},{"text":"Content8","kind":"typeIdentifier"},{"text":">, ","kind":"text"},{"text":"TableColumn","kind":"typeIdentifier","preciseIdentifier":"s:12SwiftCrossUI11TableColumnV"},{"text":"<","kind":"text"},{"text":"RowValue","kind":"typeIdentifier"},{"text":", ","kind":"text"},{"text":"Content9","kind":"typeIdentifier"},{"text":">, ","kind":"text"},{"text":"TableColumn","kind":"typeIdentifier","preciseIdentifier":"s:12SwiftCrossUI11TableColumnV"},{"text":"<","kind":"text"},{"text":"RowValue","kind":"typeIdentifier"},{"text":", ","kind":"text"},{"text":"Content10","kind":"typeIdentifier"},{"text":">) -> ","kind":"text"},{"text":"TupleTableRowContent11","kind":"typeIdentifier","preciseIdentifier":"s:12SwiftCrossUI22TupleTableRowContent11V"},{"text":"<","kind":"text"},{"text":"RowValue","kind":"typeIdentifier"},{"text":", ","kind":"text"},{"text":"Content0","kind":"typeIdentifier"},{"text":", ","kind":"text"},{"text":"Content1","kind":"typeIdentifier"},{"text":", ","kind":"text"},{"text":"Content2","kind":"typeIdentifier"},{"text":", ","kind":"text"},{"text":"Content3","kind":"typeIdentifier"},{"text":", ","kind":"text"},{"text":"Content4","kind":"typeIdentifier"},{"text":", ","kind":"text"},{"text":"Content5","kind":"typeIdentifier"},{"text":", ","kind":"text"},{"text":"Content6","kind":"typeIdentifier"},{"text":", ","kind":"text"},{"text":"Content7","kind":"typeIdentifier"},{"text":", ","kind":"text"},{"text":"Content8","kind":"typeIdentifier"},{"text":", ","kind":"text"},{"text":"Content9","kind":"typeIdentifier"},{"text":", ","kind":"text"},{"text":"Content10","kind":"typeIdentifier"},{"text":">","kind":"text"}],"identifier":"doc:\/\/SwiftCrossUI\/documentation\/SwiftCrossUI\/TableRowBuilder\/buildBlock(_:_:_:_:_:_:_:_:_:_:_:)"},"doc://SwiftCrossUI/documentation/SwiftCrossUI":{"kind":"symbol","url":"\/documentation\/swiftcrossui","type":"topic","abstract":[{"type":"text","text":"Create cross-platform desktop apps for macOS, Linux, Windows, iOS and tvOS."}],"identifier":"doc:\/\/SwiftCrossUI\/documentation\/SwiftCrossUI","title":"SwiftCrossUI","role":"collection"},"doc://SwiftCrossUI/documentation/SwiftCrossUI/TableColumn":{"identifier":"doc:\/\/SwiftCrossUI\/documentation\/SwiftCrossUI\/TableColumn","url":"\/documentation\/swiftcrossui\/tablecolumn","fragments":[{"kind":"keyword","text":"struct"},{"kind":"text","text":" "},{"kind":"identifier","text":"TableColumn"}],"role":"symbol","title":"TableColumn","navigatorTitle":[{"kind":"identifier","text":"TableColumn"}],"type":"topic","abstract":[{"text":"A labelled column with a view for each row in a table.","type":"text"}],"kind":"symbol"},"doc://SwiftCrossUI/documentation/SwiftCrossUI/TableRowBuilder":{"type":"topic","role":"symbol","fragments":[{"kind":"keyword","text":"struct"},{"kind":"text","text":" "},{"kind":"identifier","text":"TableRowBuilder"}],"navigatorTitle":[{"kind":"identifier","text":"TableRowBuilder"}],"abstract":[{"type":"text","text":"A result builder for constructing a collection of table columns."}],"url":"\/documentation\/swiftcrossui\/tablerowbuilder","kind":"symbol","identifier":"doc:\/\/SwiftCrossUI\/documentation\/SwiftCrossUI\/TableRowBuilder","title":"TableRowBuilder"},"doc://SwiftCrossUI/documentation/SwiftCrossUI/TupleTableRowContent11":{"type":"topic","url":"\/documentation\/swiftcrossui\/tupletablerowcontent11","title":"TupleTableRowContent11","navigatorTitle":[{"text":"TupleTableRowContent11","kind":"identifier"}],"role":"symbol","kind":"symbol","abstract":[],"fragments":[{"text":"struct","kind":"keyword"},{"text":" ","kind":"text"},{"text":"TupleTableRowContent11","kind":"identifier"}],"identifier":"doc:\/\/SwiftCrossUI\/documentation\/SwiftCrossUI\/TupleTableRowContent11"}}}